friendly_errors/__init__.py
friendly_errors/module.py
friendly_errors-1.0.0.dist-info/licenses/LICENSE
friendly_errors-1.0.0.dist-info/METADATA
friendly_errors-1.0.0.dist-info/WHEEL
friendly_errors-1.0.0.dist-info/top_level.txt
friendly_errors-1.0.0.dist-info/RECORD
