Metadata-Version: 2.4
Name: friendly-errors
Version: 1.0.0
Summary: A Python utility for clean, colorful, and helpful error messages with suggestions.
Home-page: https://github.com/white-darkness/friendly-errors-python
Author: Maurya Suryakant
Author-email: mauryasuryakant99@gmail.com
Classifier: Programming Language :: Python :: 3
Classifier: License :: OSI Approved :: MIT License
Classifier: Operating System :: OS Independent
Requires-Python: >=3.6
License-File: LICENSE
Requires-Dist: colorama>=0.4.6
Dynamic: author
Dynamic: author-email
Dynamic: classifier
Dynamic: description-content-type
Dynamic: home-page
Dynamic: license-file
Dynamic: requires-dist
Dynamic: requires-python
Dynamic: summary
